{
  "2026-04": {
    "total": 1594379770,
    "accounts": {
      "dsd": 188454599,
      "aaa": 40452614,
      "gggg": 271745784,
      "cc": 192852330,
      "zzz": 200783396,
      "cx": 163833336,
      "vv": 162570705,
      "mm": 10905726,
      "erdem_ada32110": 355519427,
      "yeni": 2753728,
      "ffffhh": 4508125
    }
  },
  "2026-05": {
    "total": 351846537,
    "accounts": {
      "erdem_ada32110": 106681559,
      "gggg": 43318089,
      "cc": 41116399,
      "cx": 35070442,
      "vv": 35406281,
      "zzz": 43411292,
      "vcdbvcc": 33969215,
      "cxxc": 12873260
    }
  },
  "2026-06": {
    "total": 1672863232,
    "accounts": {
      "gggg": 79630806,
      "erdem_ada32110": 284341037,
      "cc": 77931224,
      "zzz": 72358157,
      "cx": 71148016,
      "vv": 68025181,
      "vcdbvcc": 68635814,
      "cxxc": 68824706,
      "dsds": 61132194,
      "xxx": 152134330,
      "xcc": 105513273,
      "bbb": 94450492,
      "fas": 91945398,
      "bg": 92688622,
      "gas": 91714378,
      "nv": 87881615,
      "dsdsk": 104507989
    }
  }
}